LICENSE
MANIFEST.in
README.md
install.json
package.json
pyproject.toml
setup.py
tsconfig.json
yarn.lock
src/automl.tsx
src/dao.ts
src/index.ts
src/jupyter.ts
src/model.ts
src/util.ts
src/xautoml.tsx
src/components/candidate_inspections.tsx
src/components/comparison.tsx
src/components/ensemble.tsx
src/components/leaderboard.tsx
src/components/optimization_overview.tsx
src/components/search_space.tsx
src/components/automl/classification.tsx
src/components/automl/classifier_configuration.tsx
src/components/automl/dataset_configuration.tsx
src/components/automl/output.tsx
src/components/automl/panel.ts
src/components/automl/progress.tsx
src/components/automl/result.tsx
src/components/automl/timeseries.tsx
src/components/details/configuration.tsx
src/components/details/confusion_matrix.tsx
src/components/details/dataset_table.tsx
src/components/details/feature_importance.tsx
src/components/details/global_surrogate.tsx
src/components/details/hp_importance.tsx
src/components/details/local_surrogate.tsx
src/components/details/model.ts
src/components/details/performance_details.tsx
src/components/details/pipeline_hyperparameters.tsx
src/components/details/pipeline_visualization.tsx
src/components/ensemble/decision_surface.tsx
src/components/ensemble/ensemble_details.tsx
src/components/ensemble/ensemble_table.tsx
src/components/general/performance_distribution.tsx
src/components/general/performance_timeline.tsx
src/components/general/roc_curve.tsx
src/components/pc/brush.tsx
src/components/pc/constants.ts
src/components/pc/model.ts
src/components/pc/parallel_corrdinates.tsx
src/components/pc/pc_axis.tsx
src/components/pc/pc_choice.tsx
src/components/pc/pc_line.tsx
src/components/pc/util.ts
src/components/search_space/model.ts
src/components/search_space/optimization_progress.tsx
src/components/search_space/sampling_history.tsx
src/components/search_space/structure_search_graph.tsx
src/components/usu_iap/deployment-dialog.tsx
src/components/usu_iap/model.ts
xautoml.egg-info/PKG-INFO
xautoml.egg-info/SOURCES.txt
xautoml.egg-info/dependency_links.txt
xautoml.egg-info/not-zip-safe
xautoml.egg-info/requires.txt
xautoml.egg-info/top_level.txt
