Metadata-Version: 2.1
Name: xautoml
Version: 0.1.4
Summary: A JupyterLab extension to visualize and explain AutoML optimization procedures.
Home-page: https://github.com/Ennosigaeon/xautoml
Author: Marc Zoeller
Author-email: marc.zoeller@usu.com
License: BSD-3-Clause
Keywords: Jupyter,JupyterLab,JupyterLab3
Platform: Linux
Platform: Mac OS X
Platform: Windows
Classifier: License :: OSI Approved :: BSD License
Classifier: Programming Language :: Python
Classifier: Programming Language :: Python :: 3
Classifier: Programming Language :: Python :: 3.7
Classifier: Programming Language :: Python :: 3.8
Classifier: Programming Language :: Python :: 3.9
Classifier: Framework :: Jupyter
Requires-Python: >=3.6
License-File: LICENSE
